Classfile /Users/maxonfjvipon/code/java/benchmark/target/foo/after/Foo.class
  Last modified Aug 7, 2025; size 3629 bytes
  SHA-256 checksum b442dd2c29434f18accbea100af20cfcbc505863d202505e9c94cd69ac760745
public class Foo
  minor version: 0
  major version: 66
  flags: (0x0021) ACC_PUBLIC, ACC_SUPER
  this_class: #2                          // Foo
  super_class: #4                         // java/lang/Object
  interfaces: 0, fields: 0, methods: 15, attributes: 2
Constant pool:
    #1 = Utf8               Foo
    #2 = Class              #1            // Foo
    #3 = Utf8               java/lang/Object
    #4 = Class              #3            // java/lang/Object
    #5 = Utf8               <init>
    #6 = Utf8               ()V
    #7 = NameAndType        #5:#6         // "<init>":()V
    #8 = Methodref          #4.#7         // java/lang/Object."<init>":()V
    #9 = Utf8               main
   #10 = Utf8               ([Ljava/lang/String;)V
   #11 = Utf8               arg0
   #12 = Utf8               java/util/stream/IntStream
   #13 = Class              #12           // java/util/stream/IntStream
   #14 = Utf8               of
   #15 = Utf8               ([I)Ljava/util/stream/IntStream;
   #16 = NameAndType        #14:#15       // of:([I)Ljava/util/stream/IntStream;
   #17 = InterfaceMethodref #13.#16       // java/util/stream/IntStream.of:([I)Ljava/util/stream/IntStream;
   #18 = Utf8               (I)I
   #19 = MethodType         #18           //  (I)I
   #20 = Utf8               lambda$main$0
   #21 = NameAndType        #20:#18       // lambda$main$0:(I)I
   #22 = Methodref          #2.#21        // Foo.lambda$main$0:(I)I
   #23 = MethodHandle       6:#22         // REF_invokeStatic Foo.lambda$main$0:(I)I
   #24 = Utf8               java/lang/invoke/LambdaMetafactory
   #25 = Class              #24           // java/lang/invoke/LambdaMetafactory
   #26 = Utf8               metafactory
   #27 = Utf8               (Ljava/lang/invoke/MethodHandles$Lookup;Ljava/lang/String;Ljava/lang/invoke/MethodType;Ljava/lang/invoke/MethodType;Ljava/lang/invoke/MethodHandle;Ljava/lang/invoke/MethodType;)Ljava/lang/invoke/CallSite;
   #28 = NameAndType        #26:#27       // metafactory:(Ljava/lang/invoke/MethodHandles$Lookup;Ljava/lang/String;Ljava/lang/invoke/MethodType;Ljava/lang/invoke/MethodType;Ljava/lang/invoke/MethodHandle;Ljava/lang/invoke/MethodType;)Ljava/lang/invoke/CallSite;
   #29 = Methodref          #25.#28       // java/lang/invoke/LambdaMetafactory.metafactory:(Ljava/lang/invoke/MethodHandles$Lookup;Ljava/lang/String;Ljava/lang/invoke/MethodType;Ljava/lang/invoke/MethodType;Ljava/lang/invoke/MethodHandle;Ljava/lang/invoke/MethodType;)Ljava/lang/invoke/CallSite;
   #30 = MethodHandle       6:#29         // REF_invokeStatic java/lang/invoke/LambdaMetafactory.metafactory:(Ljava/lang/invoke/MethodHandles$Lookup;Ljava/lang/String;Ljava/lang/invoke/MethodType;Ljava/lang/invoke/MethodType;Ljava/lang/invoke/MethodHandle;Ljava/lang/invoke/MethodType;)Ljava/lang/invoke/CallSite;
   #31 = Utf8               applyAsInt
   #32 = Utf8               ()Ljava/util/function/IntUnaryOperator;
   #33 = NameAndType        #31:#32       // applyAsInt:()Ljava/util/function/IntUnaryOperator;
   #34 = InvokeDynamic      #0:#33        // #0:applyAsInt:()Ljava/util/function/IntUnaryOperator;
   #35 = Utf8               map
   #36 = Utf8               (Ljava/util/function/IntUnaryOperator;)Ljava/util/stream/IntStream;
   #37 = NameAndType        #35:#36       // map:(Ljava/util/function/IntUnaryOperator;)Ljava/util/stream/IntStream;
   #38 = InterfaceMethodref #13.#37       // java/util/stream/IntStream.map:(Ljava/util/function/IntUnaryOperator;)Ljava/util/stream/IntStream;
   #39 = Utf8               (I)Z
   #40 = MethodType         #39           //  (I)Z
   #41 = Utf8               lambda$main$1
   #42 = NameAndType        #41:#39       // lambda$main$1:(I)Z
   #43 = Methodref          #2.#42        // Foo.lambda$main$1:(I)Z
   #44 = MethodHandle       6:#43         // REF_invokeStatic Foo.lambda$main$1:(I)Z
   #45 = Utf8               test
   #46 = Utf8               ()Ljava/util/function/IntPredicate;
   #47 = NameAndType        #45:#46       // test:()Ljava/util/function/IntPredicate;
   #48 = InvokeDynamic      #1:#47        // #1:test:()Ljava/util/function/IntPredicate;
   #49 = Utf8               filter
   #50 = Utf8               (Ljava/util/function/IntPredicate;)Ljava/util/stream/IntStream;
   #51 = NameAndType        #49:#50       // filter:(Ljava/util/function/IntPredicate;)Ljava/util/stream/IntStream;
   #52 = InterfaceMethodref #13.#51       // java/util/stream/IntStream.filter:(Ljava/util/function/IntPredicate;)Ljava/util/stream/IntStream;
   #53 = Utf8               boxed
   #54 = Utf8               ()Ljava/util/stream/Stream;
   #55 = NameAndType        #53:#54       // boxed:()Ljava/util/stream/Stream;
   #56 = InterfaceMethodref #13.#55       // java/util/stream/IntStream.boxed:()Ljava/util/stream/Stream;
   #57 = Utf8               (Ljava/lang/Object;Ljava/lang/Object;)V
   #58 = MethodType         #57           //  (Ljava/lang/Object;Ljava/lang/Object;)V
   #59 = Utf8               distill_5645
   #60 = Utf8               (Ljava/lang/Integer;Ljava/util/function/Consumer;)V
   #61 = NameAndType        #59:#60       // distill_5645:(Ljava/lang/Integer;Ljava/util/function/Consumer;)V
   #62 = Methodref          #2.#61        // Foo.distill_5645:(Ljava/lang/Integer;Ljava/util/function/Consumer;)V
   #63 = MethodHandle       6:#62         // REF_invokeStatic Foo.distill_5645:(Ljava/lang/Integer;Ljava/util/function/Consumer;)V
   #64 = MethodType         #60           //  (Ljava/lang/Integer;Ljava/util/function/Consumer;)V
   #65 = Utf8               accept
   #66 = Utf8               ()Ljava/util/function/BiConsumer;
   #67 = NameAndType        #65:#66       // accept:()Ljava/util/function/BiConsumer;
   #68 = InvokeDynamic      #2:#67        // #2:accept:()Ljava/util/function/BiConsumer;
   #69 = Utf8               java/util/stream/Stream
   #70 = Class              #69           // java/util/stream/Stream
   #71 = Utf8               mapMulti
   #72 = Utf8               (Ljava/util/function/BiConsumer;)Ljava/util/stream/Stream;
   #73 = NameAndType        #71:#72       // mapMulti:(Ljava/util/function/BiConsumer;)Ljava/util/stream/Stream;
   #74 = InterfaceMethodref #70.#73       // java/util/stream/Stream.mapMulti:(Ljava/util/function/BiConsumer;)Ljava/util/stream/Stream;
   #75 = Utf8               (Ljava/lang/Object;)J
   #76 = MethodType         #75           //  (Ljava/lang/Object;)J
   #77 = Utf8               lambda$main$4
   #78 = Utf8               (Ljava/lang/Long;)J
   #79 = NameAndType        #77:#78       // lambda$main$4:(Ljava/lang/Long;)J
   #80 = Methodref          #2.#79        // Foo.lambda$main$4:(Ljava/lang/Long;)J
   #81 = MethodHandle       6:#80         // REF_invokeStatic Foo.lambda$main$4:(Ljava/lang/Long;)J
   #82 = MethodType         #78           //  (Ljava/lang/Long;)J
   #83 = Utf8               applyAsLong
   #84 = Utf8               ()Ljava/util/function/ToLongFunction;
   #85 = NameAndType        #83:#84       // applyAsLong:()Ljava/util/function/ToLongFunction;
   #86 = InvokeDynamic      #3:#85        // #3:applyAsLong:()Ljava/util/function/ToLongFunction;
   #87 = Utf8               mapToLong
   #88 = Utf8               (Ljava/util/function/ToLongFunction;)Ljava/util/stream/LongStream;
   #89 = NameAndType        #87:#88       // mapToLong:(Ljava/util/function/ToLongFunction;)Ljava/util/stream/LongStream;
   #90 = InterfaceMethodref #70.#89       // java/util/stream/Stream.mapToLong:(Ljava/util/function/ToLongFunction;)Ljava/util/stream/LongStream;
   #91 = Utf8               java/util/stream/LongStream
   #92 = Class              #91           // java/util/stream/LongStream
   #93 = Utf8               sum
   #94 = Utf8               ()J
   #95 = NameAndType        #93:#94       // sum:()J
   #96 = InterfaceMethodref #92.#95       // java/util/stream/LongStream.sum:()J
   #97 = Utf8               java/lang/System
   #98 = Class              #97           // java/lang/System
   #99 = Utf8               out
  #100 = Utf8               Ljava/io/PrintStream;
  #101 = NameAndType        #99:#100      // out:Ljava/io/PrintStream;
  #102 = Fieldref           #98.#101      // java/lang/System.out:Ljava/io/PrintStream;
  #103 = Utf8               %d\n
  #104 = String             #103          // %d\n
  #105 = Utf8               java/lang/Long
  #106 = Class              #105          // java/lang/Long
  #107 = Utf8               valueOf
  #108 = Utf8               (J)Ljava/lang/Long;
  #109 = NameAndType        #107:#108     // valueOf:(J)Ljava/lang/Long;
  #110 = Methodref          #106.#109     // java/lang/Long.valueOf:(J)Ljava/lang/Long;
  #111 = Utf8               java/io/PrintStream
  #112 = Class              #111          // java/io/PrintStream
  #113 = Utf8               printf
  #114 = Utf8               (Ljava/lang/String;[Ljava/lang/Object;)Ljava/io/PrintStream;
  #115 = NameAndType        #113:#114     // printf:(Ljava/lang/String;[Ljava/lang/Object;)Ljava/io/PrintStream;
  #116 = Methodref          #112.#115     // java/io/PrintStream.printf:(Ljava/lang/String;[Ljava/lang/Object;)Ljava/io/PrintStream;
  #117 = Utf8               returnsLong
  #118 = Utf8               (J)J
  #119 = Utf8               acceptsDouble
  #120 = Utf8               (D)Ljava/lang/Integer;
  #121 = Utf8               java/lang/Double
  #122 = Class              #121          // java/lang/Double
  #123 = Utf8               (D)Ljava/lang/Double;
  #124 = NameAndType        #107:#123     // valueOf:(D)Ljava/lang/Double;
  #125 = Methodref          #122.#124     // java/lang/Double.valueOf:(D)Ljava/lang/Double;
  #126 = Utf8               intValue
  #127 = Utf8               ()I
  #128 = NameAndType        #126:#127     // intValue:()I
  #129 = Methodref          #122.#128     // java/lang/Double.intValue:()I
  #130 = Utf8               java/lang/Integer
  #131 = Class              #130          // java/lang/Integer
  #132 = Utf8               (I)Ljava/lang/Integer;
  #133 = NameAndType        #107:#132     // valueOf:(I)Ljava/lang/Integer;
  #134 = Methodref          #131.#133     // java/lang/Integer.valueOf:(I)Ljava/lang/Integer;
  #135 = Utf8               filterBool
  #136 = Utf8               (Ljava/lang/Integer;)Z
  #137 = Methodref          #131.#128     // java/lang/Integer.intValue:()I
  #138 = Utf8               filterBoolean
  #139 = Utf8               (J)Ljava/lang/Boolean;
  #140 = Utf8               java/lang/Boolean
  #141 = Class              #140          // java/lang/Boolean
  #142 = Utf8               (Z)Ljava/lang/Boolean;
  #143 = NameAndType        #107:#142     // valueOf:(Z)Ljava/lang/Boolean;
  #144 = Methodref          #141.#143     // java/lang/Boolean.valueOf:(Z)Ljava/lang/Boolean;
  #145 = Utf8               bothPrimitives
  #146 = Utf8               (S)D
  #147 = Utf8               filterPrim
  #148 = Utf8               (D)Z
  #149 = Utf8               filterObject
  #150 = Utf8               (Ljava/lang/Object;)Z
  #151 = Utf8               longValue
  #152 = NameAndType        #151:#94      // longValue:()J
  #153 = Methodref          #106.#152     // java/lang/Long.longValue:()J
  #154 = Utf8               lambda$main$3
  #155 = Utf8               (Ljava/lang/Long;)Z
  #156 = Long               5l
  #158 = Utf8               lambda$main$2
  #159 = Utf8               (Ljava/lang/Integer;)Ljava/lang/Short;
  #160 = Utf8               shortValue
  #161 = Utf8               ()S
  #162 = NameAndType        #160:#161     // shortValue:()S
  #163 = Methodref          #131.#162     // java/lang/Integer.shortValue:()S
  #164 = Utf8               java/lang/Short
  #165 = Class              #164          // java/lang/Short
  #166 = Utf8               (S)Ljava/lang/Short;
  #167 = NameAndType        #107:#166     // valueOf:(S)Ljava/lang/Short;
  #168 = Methodref          #165.#167     // java/lang/Short.valueOf:(S)Ljava/lang/Short;
  #169 = Utf8               i1
  #170 = Utf8               i2
  #171 = Utf8               doubleValue
  #172 = Utf8               ()D
  #173 = NameAndType        #171:#172     // doubleValue:()D
  #174 = Methodref          #131.#173     // java/lang/Integer.doubleValue:()D
  #175 = NameAndType        #147:#148     // filterPrim:(D)Z
  #176 = Methodref          #2.#175       // Foo.filterPrim:(D)Z
  #177 = NameAndType        #158:#159     // lambda$main$2:(Ljava/lang/Integer;)Ljava/lang/Short;
  #178 = Methodref          #2.#177       // Foo.lambda$main$2:(Ljava/lang/Integer;)Ljava/lang/Short;
  #179 = Methodref          #165.#162     // java/lang/Short.shortValue:()S
  #180 = NameAndType        #145:#146     // bothPrimitives:(S)D
  #181 = Methodref          #2.#180       // Foo.bothPrimitives:(S)D
  #182 = Methodref          #122.#152     // java/lang/Double.longValue:()J
  #183 = NameAndType        #154:#155     // lambda$main$3:(Ljava/lang/Long;)Z
  #184 = Methodref          #2.#183       // Foo.lambda$main$3:(Ljava/lang/Long;)Z
  #185 = NameAndType        #117:#118     // returnsLong:(J)J
  #186 = Methodref          #2.#185       // Foo.returnsLong:(J)J
  #187 = Utf8               java/util/function/Consumer
  #188 = Class              #187          // java/util/function/Consumer
  #189 = Utf8               (Ljava/lang/Object;)V
  #190 = NameAndType        #65:#189      // accept:(Ljava/lang/Object;)V
  #191 = InterfaceMethodref #188.#190     // java/util/function/Consumer.accept:(Ljava/lang/Object;)V
  #192 = Utf8               java/lang/invoke/MethodHandles$Lookup
  #193 = Class              #192          // java/lang/invoke/MethodHandles$Lookup
  #194 = Utf8               java/lang/invoke/MethodHandles
  #195 = Class              #194          // java/lang/invoke/MethodHandles
  #196 = Utf8               Lookup
  #197 = Utf8               Code
  #198 = Utf8               MethodParameters
  #199 = Utf8               StackMapTable
  #200 = Utf8               InnerClasses
  #201 = Utf8               BootstrapMethods
{
  public Foo();
    descriptor: ()V
    flags: (0x0001) ACC_PUBLIC
    Code:
      stack=1, locals=1, args_size=1
         0: aload_0
         1: invokespecial #8                  // Method java/lang/Object."<init>":()V
         4: return

  public static void main(java.lang.String[]);
    descriptor: ([Ljava/lang/String;)V
    flags: (0x0009) ACC_PUBLIC, ACC_STATIC
    Code:
      stack=7, locals=4, args_size=1
         0: iconst_5
         1: newarray       int
         3: dup
         4: iconst_0
         5: iconst_1
         6: iastore
         7: dup
         8: iconst_1
         9: iconst_2
        10: iastore
        11: dup
        12: iconst_2
        13: iconst_4
        14: iastore
        15: dup
        16: iconst_3
        17: bipush        8
        19: iastore
        20: dup
        21: iconst_4
        22: bipush        16
        24: iastore
        25: astore_1
        26: aload_1
        27: invokestatic  #17                 // InterfaceMethod java/util/stream/IntStream.of:([I)Ljava/util/stream/IntStream;
        30: invokedynamic #34,  0             // InvokeDynamic #0:applyAsInt:()Ljava/util/function/IntUnaryOperator;
        35: invokeinterface #38,  2           // InterfaceMethod java/util/stream/IntStream.map:(Ljava/util/function/IntUnaryOperator;)Ljava/util/stream/IntStream;
        40: invokedynamic #48,  0             // InvokeDynamic #1:test:()Ljava/util/function/IntPredicate;
        45: invokeinterface #52,  2           // InterfaceMethod java/util/stream/IntStream.filter:(Ljava/util/function/IntPredicate;)Ljava/util/stream/IntStream;
        50: invokeinterface #56,  1           // InterfaceMethod java/util/stream/IntStream.boxed:()Ljava/util/stream/Stream;
        55: invokedynamic #68,  0             // InvokeDynamic #2:accept:()Ljava/util/function/BiConsumer;
        60: invokeinterface #74,  2           // InterfaceMethod java/util/stream/Stream.mapMulti:(Ljava/util/function/BiConsumer;)Ljava/util/stream/Stream;
        65: invokedynamic #86,  0             // InvokeDynamic #3:applyAsLong:()Ljava/util/function/ToLongFunction;
        70: invokeinterface #90,  2           // InterfaceMethod java/util/stream/Stream.mapToLong:(Ljava/util/function/ToLongFunction;)Ljava/util/stream/LongStream;
        75: invokeinterface #96,  1           // InterfaceMethod java/util/stream/LongStream.sum:()J
        80: lstore_2
        81: getstatic     #102                // Field java/lang/System.out:Ljava/io/PrintStream;
        84: ldc           #104                // String %d\n
        86: iconst_1
        87: anewarray     #4                  // class java/lang/Object
        90: dup
        91: iconst_0
        92: lload_2
        93: invokestatic  #110                // Method java/lang/Long.valueOf:(J)Ljava/lang/Long;
        96: aastore
        97: invokevirtual #116                // Method java/io/PrintStream.printf:(Ljava/lang/String;[Ljava/lang/Object;)Ljava/io/PrintStream;
       100: pop
       101: return
    MethodParameters:
      Name                           Flags
      arg0

  private static long returnsLong(long);
    descriptor: (J)J
    flags: (0x000a) ACC_PRIVATE, ACC_STATIC
    Code:
      stack=2, locals=2, args_size=1
         0: lload_0
         1: lreturn
    MethodParameters:
      Name                           Flags
      arg0

  private static java.lang.Integer acceptsDouble(double);
    descriptor: (D)Ljava/lang/Integer;
    flags: (0x000a) ACC_PRIVATE, ACC_STATIC
    Code:
      stack=2, locals=2, args_size=1
         0: dload_0
         1: invokestatic  #125                // Method java/lang/Double.valueOf:(D)Ljava/lang/Double;
         4: invokevirtual #129                // Method java/lang/Double.intValue:()I
         7: invokestatic  #134                // Method java/lang/Integer.valueOf:(I)Ljava/lang/Integer;
        10: areturn
    MethodParameters:
      Name                           Flags
      arg0

  private static boolean filterBool(java.lang.Integer);
    descriptor: (Ljava/lang/Integer;)Z
    flags: (0x000a) ACC_PRIVATE, ACC_STATIC
    Code:
      stack=2, locals=1, args_size=1
         0: aload_0
         1: invokevirtual #137                // Method java/lang/Integer.intValue:()I
         4: iconst_1
         5: if_icmple     12
         8: iconst_1
         9: goto          13
        12: iconst_0
        13: ireturn
      StackMapTable: number_of_entries = 2
        frame_type = 12 /* same */
        frame_type = 64 /* same_locals_1_stack_item */
          stack = [ int ]
    MethodParameters:
      Name                           Flags
      arg0

  private static java.lang.Boolean filterBoolean(long);
    descriptor: (J)Ljava/lang/Boolean;
    flags: (0x000a) ACC_PRIVATE, ACC_STATIC
    Code:
      stack=4, locals=2, args_size=1
         0: lload_0
         1: lconst_1
         2: lcmp
         3: ifle          10
         6: iconst_1
         7: goto          11
        10: iconst_0
        11: invokestatic  #144                // Method java/lang/Boolean.valueOf:(Z)Ljava/lang/Boolean;
        14: areturn
      StackMapTable: number_of_entries = 2
        frame_type = 10 /* same */
        frame_type = 64 /* same_locals_1_stack_item */
          stack = [ int ]
    MethodParameters:
      Name                           Flags
      arg0

  private static double bothPrimitives(short);
    descriptor: (S)D
    flags: (0x000a) ACC_PRIVATE, ACC_STATIC
    Code:
      stack=2, locals=1, args_size=1
         0: iload_0
         1: i2d
         2: dreturn
    MethodParameters:
      Name                           Flags
      arg0

  private static boolean filterPrim(double);
    descriptor: (D)Z
    flags: (0x000a) ACC_PRIVATE, ACC_STATIC
    Code:
      stack=1, locals=2, args_size=1
         0: iconst_1
         1: ireturn
    MethodParameters:
      Name                           Flags
      arg0

  private static boolean filterObject(java.lang.Object);
    descriptor: (Ljava/lang/Object;)Z
    flags: (0x000a) ACC_PRIVATE, ACC_STATIC
    Code:
      stack=1, locals=1, args_size=1
         0: iconst_1
         1: ireturn
    MethodParameters:
      Name                           Flags
      arg0

  private static long lambda$main$4(java.lang.Long);
    descriptor: (Ljava/lang/Long;)J
    flags: (0x100a) ACC_PRIVATE, ACC_STATIC, ACC_SYNTHETIC
    Code:
      stack=2, locals=1, args_size=1
         0: aload_0
         1: invokevirtual #153                // Method java/lang/Long.longValue:()J
         4: lreturn
    MethodParameters:
      Name                           Flags
      arg0

  private static boolean lambda$main$3(java.lang.Long);
    descriptor: (Ljava/lang/Long;)Z
    flags: (0x100a) ACC_PRIVATE, ACC_STATIC, ACC_SYNTHETIC
    Code:
      stack=4, locals=1, args_size=1
         0: aload_0
         1: invokevirtual #153                // Method java/lang/Long.longValue:()J
         4: ldc2_w        #156                // long 5l
         7: lcmp
         8: ifle          15
        11: iconst_1
        12: goto          16
        15: iconst_0
        16: ireturn
      StackMapTable: number_of_entries = 2
        frame_type = 15 /* same */
        frame_type = 64 /* same_locals_1_stack_item */
          stack = [ int ]
    MethodParameters:
      Name                           Flags
      arg0

  private static java.lang.Short lambda$main$2(java.lang.Integer);
    descriptor: (Ljava/lang/Integer;)Ljava/lang/Short;
    flags: (0x100a) ACC_PRIVATE, ACC_STATIC, ACC_SYNTHETIC
    Code:
      stack=1, locals=1, args_size=1
         0: aload_0
         1: invokevirtual #163                // Method java/lang/Integer.shortValue:()S
         4: invokestatic  #168                // Method java/lang/Short.valueOf:(S)Ljava/lang/Short;
         7: areturn
    MethodParameters:
      Name                           Flags
      arg0

  private static boolean lambda$main$1(int);
    descriptor: (I)Z
    flags: (0x100a) ACC_PRIVATE, ACC_STATIC, ACC_SYNTHETIC
    Code:
      stack=2, locals=1, args_size=1
         0: iload_0
         1: iconst_1
         2: if_icmple     9
         5: iconst_1
         6: goto          10
         9: iconst_0
        10: ireturn
      StackMapTable: number_of_entries = 2
        frame_type = 9 /* same */
        frame_type = 64 /* same_locals_1_stack_item */
          stack = [ int ]
    MethodParameters:
      Name                           Flags
      arg0

  private static int lambda$main$0(int);
    descriptor: (I)I
    flags: (0x100a) ACC_PRIVATE, ACC_STATIC, ACC_SYNTHETIC
    Code:
      stack=2, locals=1, args_size=1
         0: iload_0
         1: iconst_1
         2: iadd
         3: ireturn
    MethodParameters:
      Name                           Flags
      arg0

  private static void distill_5645(java.lang.Integer, java.util.function.Consumer);
    descriptor: (Ljava/lang/Integer;Ljava/util/function/Consumer;)V
    flags: (0x100a) ACC_PRIVATE, ACC_STATIC, ACC_SYNTHETIC
    Code:
      stack=4, locals=2, args_size=2
         0: aload_0
         1: dup
         2: invokevirtual #174                // Method java/lang/Integer.doubleValue:()D
         5: invokestatic  #176                // Method filterPrim:(D)Z
         8: ifne          12
        11: return
        12: invokestatic  #178                // Method lambda$main$2:(Ljava/lang/Integer;)Ljava/lang/Short;
        15: invokevirtual #179                // Method java/lang/Short.shortValue:()S
        18: invokestatic  #181                // Method bothPrimitives:(S)D
        21: invokestatic  #125                // Method java/lang/Double.valueOf:(D)Ljava/lang/Double;
        24: invokevirtual #182                // Method java/lang/Double.longValue:()J
        27: dup2
        28: invokestatic  #110                // Method java/lang/Long.valueOf:(J)Ljava/lang/Long;
        31: invokestatic  #184                // Method lambda$main$3:(Ljava/lang/Long;)Z
        34: ifne          38
        37: return
        38: dup2
        39: l2d
        40: invokestatic  #176                // Method filterPrim:(D)Z
        43: ifne          47
        46: return
        47: invokevirtual #153                // Method java/lang/Long.longValue:()J
        50: invokestatic  #186                // Method returnsLong:(J)J
        53: invokestatic  #110                // Method java/lang/Long.valueOf:(J)Ljava/lang/Long;
        56: aload_1
        57: swap
        58: invokeinterface #191,  2          // InterfaceMethod java/util/function/Consumer.accept:(Ljava/lang/Object;)V
        63: return
      StackMapTable: number_of_entries = 3
        frame_type = 76 /* same_locals_1_stack_item */
          stack = [ class java/lang/Integer ]
        frame_type = 89 /* same_locals_1_stack_item */
          stack = [ long ]
        frame_type = 72 /* same_locals_1_stack_item */
          stack = [ long ]
    MethodParameters:
      Name                           Flags
      i1
      i2
}
InnerClasses:
  public static final #196= #193 of #195; // Lookup=class java/lang/invoke/MethodHandles$Lookup of class java/lang/invoke/MethodHandles
BootstrapMethods:
  0: #30 REF_invokeStatic java/lang/invoke/LambdaMetafactory.metafactory:(Ljava/lang/invoke/MethodHandles$Lookup;Ljava/lang/String;Ljava/lang/invoke/MethodType;Ljava/lang/invoke/MethodType;Ljava/lang/invoke/MethodHandle;Ljava/lang/invoke/MethodType;)Ljava/lang/invoke/CallSite;
    Method arguments:
      #19 (I)I
      #23 REF_invokeStatic Foo.lambda$main$0:(I)I
      #19 (I)I
  1: #30 REF_invokeStatic java/lang/invoke/LambdaMetafactory.metafactory:(Ljava/lang/invoke/MethodHandles$Lookup;Ljava/lang/String;Ljava/lang/invoke/MethodType;Ljava/lang/invoke/MethodType;Ljava/lang/invoke/MethodHandle;Ljava/lang/invoke/MethodType;)Ljava/lang/invoke/CallSite;
    Method arguments:
      #40 (I)Z
      #44 REF_invokeStatic Foo.lambda$main$1:(I)Z
      #40 (I)Z
  2: #30 REF_invokeStatic java/lang/invoke/LambdaMetafactory.metafactory:(Ljava/lang/invoke/MethodHandles$Lookup;Ljava/lang/String;Ljava/lang/invoke/MethodType;Ljava/lang/invoke/MethodType;Ljava/lang/invoke/MethodHandle;Ljava/lang/invoke/MethodType;)Ljava/lang/invoke/CallSite;
    Method arguments:
      #58 (Ljava/lang/Object;Ljava/lang/Object;)V
      #63 REF_invokeStatic Foo.distill_5645:(Ljava/lang/Integer;Ljava/util/function/Consumer;)V
      #64 (Ljava/lang/Integer;Ljava/util/function/Consumer;)V
  3: #30 REF_invokeStatic java/lang/invoke/LambdaMetafactory.metafactory:(Ljava/lang/invoke/MethodHandles$Lookup;Ljava/lang/String;Ljava/lang/invoke/MethodType;Ljava/lang/invoke/MethodType;Ljava/lang/invoke/MethodHandle;Ljava/lang/invoke/MethodType;)Ljava/lang/invoke/CallSite;
    Method arguments:
      #76 (Ljava/lang/Object;)J
      #81 REF_invokeStatic Foo.lambda$main$4:(Ljava/lang/Long;)J
      #82 (Ljava/lang/Long;)J
